pipetorch/__init__.py
pipetorch/gpu.py
pipetorch/helper.py
pipetorch/version.py
pipetorch/data/__init__.py
pipetorch/data/databunch.py
pipetorch/data/datasets.py
pipetorch/data/dframe.py
pipetorch/data/dset.py
pipetorch/data/google_images_download.py
pipetorch/data/helper.py
pipetorch/data/imagedatasets.py
pipetorch/data/imagedframe.py
pipetorch/data/kagglereader.py
pipetorch/data/textcollection.py
pipetorch/data/transformabledataset.py
pipetorch/data/datasets/dam_outflow.csv
pipetorch/data/datasets/realestate.csv
pipetorch/evaluate/__init__.py
pipetorch/evaluate/evaluate.py
pipetorch/evaluate/evaluateresults.py
pipetorch/evaluate/study.py
pipetorch/model/__init__.py
pipetorch/model/convnet.py
pipetorch/model/perceptron.py
pipetorch/model/transfer.py
pipetorch/notebook/__init__.py
pipetorch/notebook/tools.py
pipetorch/train/__init__.py
pipetorch/train/helper.py
pipetorch/train/study.py
pipetorch/train/study_old.py
pipetorch/train/trainer.py
pipetorch/train/tuner.py
pipetorch-0.17b2.dist-info/LICENSE.txt
pipetorch-0.17b2.dist-info/METADATA
pipetorch-0.17b2.dist-info/WHEEL
pipetorch-0.17b2.dist-info/top_level.txt
pipetorch-0.17b2.dist-info/RECORD
